config/__init__.py
config/env_enum.py
controller/__init__.py
controller/app.py
controller/email_controller.py
data_model/__init__.py
data_model/bill.py
data_model/email_data.py
data_model/user_data.py
http_adapter/__init__.py
http_adapter/ssl3_http_adapter.py
scripts/__init__.py
scripts/email_sender.py
service/__init__.py
service/email_service.py
service/tauron_scrape_service.py
soup/__init__.py
soup/html_parser.py
util/__init__.py
util/date.py
util/formatter.py
util/messages.py
util/singleton.py
tauron_scraper_renanrgs-0.0.19.dist-info/LICENSE
tauron_scraper_renanrgs-0.0.19.dist-info/METADATA
tauron_scraper_renanrgs-0.0.19.dist-info/WHEEL
tauron_scraper_renanrgs-0.0.19.dist-info/top_level.txt
tauron_scraper_renanrgs-0.0.19.dist-info/RECORD
