Metadata-Version: 2.1
Name: tauron-scraper-renanrgs
Version: 0.0.19
Summary: Tauron Web Scraper
Home-page: https://github.com/renanrgs/tauron_web_scraper
Author: Renan Silva
Author-email: renan.rgsilva@gmail.com
Classifier: Programming Language :: Python :: 3
Classifier: License :: OSI Approved :: MIT License
Classifier: Operating System :: OS Independent
Requires-Python: >=3.10.4
License-File: LICENSE
Requires-Dist: beautifulsoup4 (<=4.11.1)
Requires-Dist: Flask (<=2.1.2)
Requires-Dist: requests (<=2.27.1)
Requires-Dist: urllib3 (<=1.26.9)
Requires-Dist: yagmail (>=0.15.277)
